INSTALL.rst
LICENSE
MANIFEST.in
README.rst
VERSION
requirements.txt
setup.py
tasks.py
src/django_viewpack.egg-info/PKG-INFO
src/django_viewpack.egg-info/SOURCES.txt
src/django_viewpack.egg-info/dependency_links.txt
src/django_viewpack.egg-info/not-zip-safe
src/django_viewpack.egg-info/requires.txt
src/django_viewpack.egg-info/top_level.txt
src/test_app/__init__.py
src/test_app/admin.py
src/test_app/apps.py
src/test_app/models.py
src/test_app/tests.py
src/test_app/views.py
src/test_app/migrations/0001_initial.py
src/test_app/migrations/__init__.py
src/test_server/__init__.py
src/test_server/settings.py
src/test_server/urls.py
src/test_server/wsgi.py
src/viewpack/__init__.py
src/viewpack/__meta__.py
src/viewpack/apps.py
src/viewpack/decorators.py
src/viewpack/types.py
src/viewpack/utils.py
src/viewpack/migrations/__init__.py
src/viewpack/templates/viewpack
src/viewpack/templates/viewpack/base.jinja2
src/viewpack/templates/viewpack/crud/base.jinja2
src/viewpack/templates/viewpack/crud/config-base.jinja2
src/viewpack/templates/viewpack/crud/create-base.jinja2
src/viewpack/templates/viewpack/crud/delete-base.jinja2
src/viewpack/templates/viewpack/crud/detail-base.jinja2
src/viewpack/templates/viewpack/crud/form-base.jinja2
src/viewpack/templates/viewpack/crud/form.jinja2
src/viewpack/templates/viewpack/crud/list-base.jinja2
src/viewpack/templates/viewpack/crud/update-base.jinja2
src/viewpack/tests/__init__.py
src/viewpack/tests/test_viewgroups.py
src/viewpack/views/__init__.py
src/viewpack/views/base.py
src/viewpack/views/childviews.py
src/viewpack/views/parentviews.py